frico/__init__.py
frico/bitstring.py
frico/blocks.py
frico/devices.py
frico/parsers.py
frico/py.typed
frico/typing.py
frico-0.0.7.dist-info/LICENSE
frico-0.0.7.dist-info/METADATA
frico-0.0.7.dist-info/WHEEL
frico-0.0.7.dist-info/top_level.txt
frico-0.0.7.dist-info/RECORD
