Metadata-Version: 2.1
Name: frico
Version: 0.0.7
Summary: A framework for accessing integrated circuits via descriptors
Home-page: https://github.com/mmangus/frico
Author: Michael Mangus
Author-email: mmangus@gmail.com
License: UNKNOWN
Project-URL: Bug Tracker, https://github.com/mmangus/frico/issues
Platform: UNKNOWN
Classifier: Programming Language :: Python :: 3
Classifier: License :: OSI Approved :: MIT License
Classifier: Operating System :: OS Independent
Requires-Python: >=3.6
Requires-Dist: smbus2 (>=0.4.1)
